XinlingZhengzhi/Dockerfile
XinlingZhengzhi/README.md
XinlingZhengzhi/__init__.py
XinlingZhengzhi/__main__.py
XinlingZhengzhi/file.epub
XinlingZhengzhi/index.html
XinlingZhengzhi/css/__init__.py
XinlingZhengzhi/css/annotations.css
XinlingZhengzhi/css/main.css
XinlingZhengzhi/css/normalize.css
XinlingZhengzhi/css/popup.css
XinlingZhengzhi/font/__init__.py
XinlingZhengzhi/font/fontello.eot
XinlingZhengzhi/font/fontello.svg
XinlingZhengzhi/font/fontello.ttf
XinlingZhengzhi/font/fontello.woff
XinlingZhengzhi/img/__init__.py
XinlingZhengzhi/img/annotator-glyph-sprite.png
XinlingZhengzhi/img/annotator-icon-sprite.png
XinlingZhengzhi/img/apple-touch-icon.png
XinlingZhengzhi/img/cancelfullscreen.png
XinlingZhengzhi/img/close.png
XinlingZhengzhi/img/fullscreen.png
XinlingZhengzhi/img/loader.gif
XinlingZhengzhi/img/menu-icon.png
XinlingZhengzhi/img/save.png
XinlingZhengzhi/img/saved.png
XinlingZhengzhi/img/settings-s.png
XinlingZhengzhi/img/settings.png
XinlingZhengzhi/img/star.png
XinlingZhengzhi/js/__init__.py
XinlingZhengzhi/js/epub.js
XinlingZhengzhi/js/epub.min.js
XinlingZhengzhi/js/epub.min.map
XinlingZhengzhi/js/hooks.min.js
XinlingZhengzhi/js/hooks.min.map
XinlingZhengzhi/js/reader.js
XinlingZhengzhi/js/reader.js.map
XinlingZhengzhi/js/reader.min.js
XinlingZhengzhi/js/reader.min.map
XinlingZhengzhi/js/hooks/__init__.py
XinlingZhengzhi/js/hooks/extensions/__init__.py
XinlingZhengzhi/js/hooks/extensions/highlight.js
XinlingZhengzhi/js/libs/__init__.py
XinlingZhengzhi/js/libs/jquery.min.js
XinlingZhengzhi/js/libs/localforage.min.js
XinlingZhengzhi/js/libs/screenfull.js
XinlingZhengzhi/js/libs/screenfull.min.js
XinlingZhengzhi/js/libs/zip.min.js
XinlingZhengzhi/js/plugins/__init__.py
XinlingZhengzhi/js/plugins/hypothesis.js
XinlingZhengzhi/js/plugins/search.js
xinling_zhengzhi-2022.10.9.1.dist-info/METADATA
xinling_zhengzhi-2022.10.9.1.dist-info/WHEEL
xinling_zhengzhi-2022.10.9.1.dist-info/entry_points.txt
xinling_zhengzhi-2022.10.9.1.dist-info/top_level.txt
xinling_zhengzhi-2022.10.9.1.dist-info/RECORD
